simple_elmo/__init__.py
simple_elmo/data.py
simple_elmo/elmo.py
simple_elmo/elmo_helpers.py
simple_elmo/model.py
simple_elmo/training.py
simple_elmo/vocabulary.py
simple_elmo-0.9.2.dist-info/LICENSE
simple_elmo-0.9.2.dist-info/METADATA
simple_elmo-0.9.2.dist-info/WHEEL
simple_elmo-0.9.2.dist-info/top_level.txt
simple_elmo-0.9.2.dist-info/RECORD
