Metadata-Version: 2.1
Name: simple-elmo
Version: 0.9.2
Summary: Handy library to work with pre-trained ELMo embeddings in TensorFlow
Home-page: https://github.com/ltgoslo/simple_elmo
Author: Andrey Kutuzov
Author-email: andreku@ifi.uio.no
Classifier: Programming Language :: Python :: 3
Classifier: License :: OSI Approved :: GNU General Public License v3 (GPLv3)
Classifier: Operating System :: OS Independent
Classifier: Topic :: Scientific/Engineering :: Artificial Intelligence
Classifier: Topic :: Utilities
Requires-Python: >=3.6
License-File: LICENSE
Requires-Dist: h5py
Requires-Dist: numpy
Requires-Dist: smart-open (>1.8.1)
Requires-Dist: pandas
Requires-Dist: scipy
Provides-Extra: tf
Requires-Dist: tensorflow (>=1.15.0) ; extra == 'tf'
Provides-Extra: tf_gpu
Requires-Dist: tensorflow-gpu (>=1.15.0) ; extra == 'tf_gpu'
